twccli/__init__.py
twccli/errorhandler.py
twccli/twccli-complete.sh
twccli/twccli.py
twccli/version.py
twccli/commands/ch.py
twccli/commands/config.py
twccli/commands/cp.py
twccli/commands/info.py
twccli/commands/ls.py
twccli/commands/mk.py
twccli/commands/net.py
twccli/commands/rm.py
twccli/examples/__init__.py
twccli/examples/encoding.sh
twccli/examples/gpu_cntr.py
twccli/examples/s3.py
twccli/tests/__init__.py
twccli/tests/test__session.py
twccli/tests/test_ccs.py
twccli/tests/test_cos.py
twccli/tests/test_util.py
twccli/tests/test_vcs.py
twccli/twcc/__init__.py
twccli/twcc/clidriver.py
twccli/twcc/session.py
twccli/twcc/util.py
twccli/twcc/services/__init__.py
twccli/twcc/services/base.py
twccli/twcc/services/compute.py
twccli/twcc/services/compute_util.py
twccli/twcc/services/generic.py
twccli/twcc/services/network.py
twccli/twcc/services/s3_tools.py
twccli/twcc/services/solutions.py
twccli/twcc/services/storage.py
twccli/yaml/TWCC_API.yaml
twccli/yaml/logging.yaml
TWCC_CLI-0.6.1.dist-info/LICENSE
TWCC_CLI-0.6.1.dist-info/METADATA
TWCC_CLI-0.6.1.dist-info/WHEEL
TWCC_CLI-0.6.1.dist-info/entry_points.txt
TWCC_CLI-0.6.1.dist-info/top_level.txt
TWCC_CLI-0.6.1.dist-info/zip-safe
TWCC_CLI-0.6.1.dist-info/RECORD
