Metadata-Version: 2.1
Name: TWCC-CLI
Version: 0.6.1
Summary: TWCC-CLI is a toolkit for operating TWCC resources.
Home-page: https://github.com/TW-NCHC/TWCC-CLI
Author: TWS TWCC-CLI Team
Author-email: isupport@twcc.ai
License: Apache License 2.0
Platform: UNKNOWN
Classifier: Development Status :: 2 - Pre-Alpha
Classifier: Intended Audience :: Developers
Classifier: Intended Audience :: System Administrators
Classifier: License :: OSI Approved :: Apache Software License
Classifier: Programming Language :: Python
Classifier: Programming Language :: Python :: 3.6
Classifier: Programming Language :: Python :: 3.7
Classifier: Programming Language :: Python :: 3.8
Classifier: Programming Language :: Python :: 3.9
License-File: LICENSE
Requires-Dist: sphinx-click
Requires-Dist: myst-parser
Requires-Dist: docutils (==0.18)
Requires-Dist: loguru
Requires-Dist: jmespath
Requires-Dist: netaddr
Requires-Dist: pytz
Requires-Dist: boto3
Requires-Dist: botocore
Requires-Dist: certifi
Requires-Dist: chardet (<5.0.0)
Requires-Dist: Click (==7.0)
Requires-Dist: colorclass
Requires-Dist: idna
Requires-Dist: Pygments
Requires-Dist: python-dateutil
Requires-Dist: PyYAML
Requires-Dist: regex
Requires-Dist: requests (>=2.23.0)
Requires-Dist: s3transfer
Requires-Dist: six
Requires-Dist: termcolor
Requires-Dist: terminaltables
Requires-Dist: tqdm
Requires-Dist: urllib3
Requires-Dist: wcwidth
Requires-Dist: distro
Requires-Dist: feedparser
